{
  "ABIRoot": {
    "kind": "Root",
    "name": "TopLevel",
    "printedName": "TopLevel",
    "children": [
      {
        "kind": "Import",
        "name": "UIKit",
        "printedName": "UIKit",
        "declKind": "Import",
        "moduleName": "BlueStackSDK",
        "declAttributes": [
          "RawDocComment"
        ]
      },
      {
        "kind": "Import",
        "name": "WebKit",
        "printedName": "WebKit",
        "declKind": "Import",
        "moduleName": "BlueStackSDK"
      },
      {
        "kind": "TypeDecl",
        "name": "UserAgentProvider",
        "printedName": "UserAgentProvider",
        "children": [
          {
            "kind": "Var",
            "name": "shared",
            "printedName": "shared",
            "children": [
              {
                "kind": "TypeNominal",
                "name": "UserAgentProvider",
                "printedName": "BlueStackSDK.UserAgentProvider",
                "usr": "c:@M@BlueStackSDK@objc(cs)UserAgentProvider"
              }
            ],
            "declKind": "Var",
            "usr": "c:@M@BlueStackSDK@objc(cs)UserAgentProvider(cpy)shared",
            "mangledName": "$s12BlueStackSDK17UserAgentProviderC6sharedACvpZ",
            "moduleName": "BlueStackSDK",
            "static": true,
            "declAttributes": [
              "HasInitialValue",
              "Final",
              "HasStorage",
              "AccessControl",
              "ObjC"
            ],
            "isLet": true,
            "hasStorage": true,
            "accessors": [
              {
                "kind": "Accessor",
                "name": "Get",
                "printedName": "Get()",
                "children": [
                  {
                    "kind": "TypeNominal",
                    "name": "UserAgentProvider",
                    "printedName": "BlueStackSDK.UserAgentProvider",
                    "usr": "c:@M@BlueStackSDK@objc(cs)UserAgentProvider"
                  }
                ],
                "declKind": "Accessor",
                "usr": "c:@M@BlueStackSDK@objc(cs)UserAgentProvider(cm)shared",
                "mangledName": "$s12BlueStackSDK17UserAgentProviderC6sharedACvgZ",
                "moduleName": "BlueStackSDK",
                "static": true,
                "implicit": true,
                "declAttributes": [
                  "Final",
                  "ObjC"
                ],
                "accessorKind": "get"
              }
            ]
          },
          {
            "kind": "Function",
            "name": "loadAgent",
            "printedName": "loadAgent()",
            "children": [
              {
                "kind": "TypeNominal",
                "name": "Void",
                "printedName": "()"
              }
            ],
            "declKind": "Func",
            "usr": "c:@M@BlueStackSDK@objc(cs)UserAgentProvider(im)loadAgent",
            "mangledName": "$s12BlueStackSDK17UserAgentProviderC04loadE0yyF",
            "moduleName": "BlueStackSDK",
            "declAttributes": [
              "AccessControl",
              "ObjC"
            ],
            "funcSelfKind": "NonMutating"
          },
          {
            "kind": "Function",
            "name": "getUserAgent",
            "printedName": "getUserAgent()",
            "children": [
              {
                "kind": "TypeNominal",
                "name": "Optional",
                "printedName": "Swift.String?",
                "children": [
                  {
                    "kind": "TypeNominal",
                    "name": "String",
                    "printedName": "Swift.String",
                    "usr": "s:SS"
                  }
                ],
                "usr": "s:Sq"
              }
            ],
            "declKind": "Func",
            "usr": "c:@M@BlueStackSDK@objc(cs)UserAgentProvider(cm)getUserAgent",
            "mangledName": "$s12BlueStackSDK17UserAgentProviderC03getdE0SSSgyFZ",
            "moduleName": "BlueStackSDK",
            "static": true,
            "declAttributes": [
              "AccessControl",
              "ObjC"
            ],
            "funcSelfKind": "NonMutating"
          },
          {
            "kind": "Constructor",
            "name": "init",
            "printedName": "init()",
            "children": [
              {
                "kind": "TypeNominal",
                "name": "UserAgentProvider",
                "printedName": "BlueStackSDK.UserAgentProvider",
                "usr": "c:@M@BlueStackSDK@objc(cs)UserAgentProvider"
              }
            ],
            "declKind": "Constructor",
            "usr": "c:@M@BlueStackSDK@objc(cs)UserAgentProvider(im)init",
            "mangledName": "$s12BlueStackSDK17UserAgentProviderCACycfc",
            "moduleName": "BlueStackSDK",
            "overriding": true,
            "implicit": true,
            "objc_name": "init",
            "declAttributes": [
              "Dynamic",
              "ObjC",
              "Override"
            ],
            "init_kind": "Designated"
          }
        ],
        "declKind": "Class",
        "usr": "c:@M@BlueStackSDK@objc(cs)UserAgentProvider",
        "mangledName": "$s12BlueStackSDK17UserAgentProviderC",
        "moduleName": "BlueStackSDK",
        "declAttributes": [
          "AccessControl",
          "ObjC"
        ],
        "superclassUsr": "c:objc(cs)NSObject",
        "inheritsConvenienceInitializers": true,
        "superclassNames": [
          "ObjectiveC.NSObject"
        ],
        "conformances": [
          {
            "kind": "Conformance",
            "name": "Equatable",
            "printedName": "Equatable",
            "usr": "s:SQ",
            "mangledName": "$sSQ"
          },
          {
            "kind": "Conformance",
            "name": "Hashable",
            "printedName": "Hashable",
            "usr": "s:SH",
            "mangledName": "$sSH"
          },
          {
            "kind": "Conformance",
            "name": "CVarArg",
            "printedName": "CVarArg",
            "usr": "s:s7CVarArgP",
            "mangledName": "$ss7CVarArgP"
          },
          {
            "kind": "Conformance",
            "name": "_KeyValueCodingAndObservingPublishing",
            "printedName": "_KeyValueCodingAndObservingPublishing",
            "usr": "s:10Foundation37_KeyValueCodingAndObservingPublishingP",
            "mangledName": "$s10Foundation37_KeyValueCodingAndObservingPublishingP"
          },
          {
            "kind": "Conformance",
            "name": "_KeyValueCodingAndObserving",
            "printedName": "_KeyValueCodingAndObserving",
            "usr": "s:10Foundation27_KeyValueCodingAndObservingP",
            "mangledName": "$s10Foundation27_KeyValueCodingAndObservingP"
          },
          {
            "kind": "Conformance",
            "name": "CustomStringConvertible",
            "printedName": "CustomStringConvertible",
            "usr": "s:s23CustomStringConvertibleP",
            "mangledName": "$ss23CustomStringConvertibleP"
          },
          {
            "kind": "Conformance",
            "name": "CustomDebugStringConvertible",
            "printedName": "CustomDebugStringConvertible",
            "usr": "s:s28CustomDebugStringConvertibleP",
            "mangledName": "$ss28CustomDebugStringConvertibleP"
          }
        ]
      }
    ],
    "json_format_version": 8
  },
  "ConstValues": []
}